ALS_FP/__init__.py
ALS_FP/__version__.py
ALS_FP/ALS/__init__.py
ALS_FP/ALS/New_Interface/New_Dig_Int_L3.py
ALS_FP/ALS/New_Interface/New_L3_Int.py
ALS_FP/ALS/New_Interface/__init__.py
ALS_FP/ALS/New_template/Single_FW_with_Core_Switch.py
ALS_FP/ALS/New_template/Single_FW_with_VLAN.py
ALS_FP/ALS/New_template/__init__.py
ALS_FP/Library/__init__.py
ALS_FP/Library/libr.py
smc/__init__.py
smc/__version__.py
smc/compat.py
smc/actions/__init__.py
smc/administration/__init__.py
smc/administration/access_rights.py
smc/administration/license.py
smc/administration/monitoring_status.py
smc/administration/reports.py
smc/administration/role.py
smc/administration/scheduled_tasks.py
smc/administration/system.py
smc/administration/system_properties.py
smc/administration/tasks.py
smc/administration/upcoming_event.py
smc/administration/updates.py
smc/administration/certificates/__init__.py
smc/administration/certificates/tls.py
smc/administration/certificates/tls_common.py
smc/administration/certificates/vpn.py
smc/administration/user_auth/__init__.py
smc/administration/user_auth/servers.py
smc/administration/user_auth/users.py
smc/api/__init__.py
smc/api/common.py
smc/api/configloader.py
smc/api/entry_point.py
smc/api/exceptions.py
smc/api/session.py
smc/api/web.py
smc/base/__init__.py
smc/base/collection.py
smc/base/decorators.py
smc/base/mixins.py
smc/base/model.py
smc/base/structs.py
smc/base/util.py
smc/core/__init__.py
smc/core/addon.py
smc/core/collection.py
smc/core/contact_address.py
smc/core/engine.py
smc/core/engine_vss.py
smc/core/engines.py
smc/core/general.py
smc/core/ha_management.py
smc/core/hardware.py
smc/core/interfaces.py
smc/core/lldp.py
smc/core/node.py
smc/core/resource.py
smc/core/route.py
smc/core/sub_interfaces.py
smc/core/waiters.py
smc/elements/__init__.py
smc/elements/alerts.py
smc/elements/group.py
smc/elements/helpers.py
smc/elements/netlink.py
smc/elements/network.py
smc/elements/other.py
smc/elements/profiles.py
smc/elements/protocols.py
FP_SMC_ALS_test1-0.0.1.dist-info/LICENSE
FP_SMC_ALS_test1-0.0.1.dist-info/METADATA
FP_SMC_ALS_test1-0.0.1.dist-info/WHEEL
FP_SMC_ALS_test1-0.0.1.dist-info/top_level.txt
FP_SMC_ALS_test1-0.0.1.dist-info/RECORD
