Metadata-Version: 2.1
Name: FP-SMC-ALS-test1
Version: 0.0.1
Summary: ALS Forcepoint SMC
Author: Raju K
Author-email: raju.kvn0694@gmail.com
Keywords: SMC,FP,Forcepoint,NGFW
Classifier: Development Status :: 1 - Planning
Classifier: Intended Audience :: Developers
Classifier: Programming Language :: Python :: 3
Classifier: Operating System :: Unix
Classifier: Operating System :: MacOS :: MacOS X
Classifier: Operating System :: Microsoft :: Windows
License-File: LICENSE
